spatialcore/__init__.py
spatialcore/annotation/__init__.py
spatialcore/annotation/acquisition.py
spatialcore/annotation/annotate.py
spatialcore/annotation/cellxgene.py
spatialcore/annotation/confidence.py
spatialcore/annotation/discovery.py
spatialcore/annotation/expression.py
spatialcore/annotation/loading.py
spatialcore/annotation/markers.py
spatialcore/annotation/ontology.py
spatialcore/annotation/patterns.py
spatialcore/annotation/pipeline.py
spatialcore/annotation/synapse.py
spatialcore/annotation/training.py
spatialcore/annotation/validation.py
spatialcore/core/__init__.py
spatialcore/core/cache.py
spatialcore/core/logging.py
spatialcore/core/metadata.py
spatialcore/core/utils.py
spatialcore/data/gene_mappings/ensembl_to_hugo_human.tsv
spatialcore/data/markers/canonical_markers.json
spatialcore/data/ontology_mappings/ontology_index.json
spatialcore/nmf/__init__.py
spatialcore/nmf/spanmf.py
spatialcore/plotting/__init__.py
spatialcore/plotting/benchmark.py
spatialcore/plotting/celltype.py
spatialcore/plotting/confidence.py
spatialcore/plotting/nmf.py
spatialcore/plotting/spatial.py
spatialcore/plotting/utils.py
spatialcore/plotting/validation.py
spatialcore/r_bridge/__init__.py
spatialcore/r_bridge/subprocess_runner.py
spatialcore/spatial/__init__.py
spatialcore/spatial/_neighbors.py
spatialcore/spatial/autocorrelation.py
spatialcore/spatial/distance.py
spatialcore/spatial/domains.py
spatialcore/spatial/neighborhoods.py
spatialcore/stats/__init__.py
spatialcore/stats/_thresholding.py
spatialcore/stats/classify.py
spatialcore-0.4.5.dist-info/licenses/LICENSE
spatialcore-0.4.5.dist-info/METADATA
spatialcore-0.4.5.dist-info/WHEEL
spatialcore-0.4.5.dist-info/top_level.txt
spatialcore-0.4.5.dist-info/RECORD
