Metadata-Version: 2.4
Name: spatialcore
Version: 0.4.5
Summary: Standardized spatial statistics tools for computational biology
Author: SpatialCore Contributors
License-Expression: Apache-2.0
Project-URL: Homepage, https://github.com/mcap91/SpatialCore
Project-URL: Documentation, https://mcap91.github.io/SpatialCore
Project-URL: Repository, https://github.com/mcap91/SpatialCore
Project-URL: Issues, https://github.com/mcap91/SpatialCore/issues
Keywords: spatial-transcriptomics,single-cell,bioinformatics,scanpy,squidpy,xenium,cosmx,visium
Classifier: Development Status :: 3 - Alpha
Classifier: Intended Audience :: Science/Research
Classifier: Operating System :: OS Independent
Classifier: Programming Language :: Python :: 3
Classifier: Programming Language :: Python :: 3.10
Classifier: Programming Language :: Python :: 3.11
Classifier: Programming Language :: Python :: 3.12
Classifier: Topic :: Scientific/Engineering :: Bio-Informatics
Requires-Python: >=3.10
License-File: LICENSE
Requires-Dist: anndata>=0.10.0
Requires-Dist: scanpy>=1.9.0
Requires-Dist: squidpy>=1.3.0
Requires-Dist: numpy>=1.21.0
Requires-Dist: pandas>=1.5.0
Requires-Dist: scipy>=1.9.0
Requires-Dist: scikit-learn>=1.0.0
Requires-Dist: matplotlib>=3.5.0
Requires-Dist: seaborn>=0.12.0
Requires-Dist: celltypist>=1.6.0
Provides-Extra: dev
Requires-Dist: pytest>=7.0.0; extra == "dev"
Requires-Dist: pytest-cov>=4.0.0; extra == "dev"
Requires-Dist: black>=23.0.0; extra == "dev"
Requires-Dist: ruff>=0.1.0; extra == "dev"
Requires-Dist: mypy>=1.0.0; extra == "dev"
Requires-Dist: pyyaml>=6.0.0; extra == "dev"
Requires-Dist: mkdocs>=1.5.0; extra == "dev"
Requires-Dist: mkdocs-material>=9.0.0; extra == "dev"
Requires-Dist: mkdocs-glightbox>=0.3.0; extra == "dev"
Requires-Dist: mkdocstrings[python]>=0.24.0; extra == "dev"
Dynamic: license-file
